assertwt.py
AssertWT-2.3.1.dist-info/LICENSE
AssertWT-2.3.1.dist-info/METADATA
AssertWT-2.3.1.dist-info/WHEEL
AssertWT-2.3.1.dist-info/top_level.txt
AssertWT-2.3.1.dist-info/zip-safe
AssertWT-2.3.1.dist-info/RECORD
