Metadata-Version: 2.1
Name: AssertWT
Version: 2.3.1
Summary: Run a Python script in Windows Terminal wt.exe
Author-email: cuzi <cuzi@openmail.cc>
License: Unlicense
Project-URL: Homepage, https://github.com/cvzi/AssertWT
Project-URL: Documentation, https://assertwt.readthedocs.io
Project-URL: Downloads, https://pypi.org/project/AssertWT/
Classifier: Development Status :: 5 - Production/Stable
Classifier: Programming Language :: Python
Classifier: Programming Language :: Python :: 3
Classifier: Programming Language :: Python :: 3.6
Classifier: Programming Language :: Python :: 3.7
Classifier: Programming Language :: Python :: 3.8
Classifier: Programming Language :: Python :: 3.9
Classifier: Programming Language :: Python :: 3.10
Classifier: Programming Language :: Python :: 3.11
Classifier: License :: OSI Approved :: The Unlicense (Unlicense)
License-File: LICENSE
